gpterminal/__init__.py
gpterminal/checks.py
gpterminal/config.py
gpterminal/gpt_settings.py
gpterminal/gpt_terminal.py
gpterminal/menu.py
gpt_terminal-0.1.11.dist-info/LICENSE
gpt_terminal-0.1.11.dist-info/METADATA
gpt_terminal-0.1.11.dist-info/WHEEL
gpt_terminal-0.1.11.dist-info/entry_points.txt
gpt_terminal-0.1.11.dist-info/top_level.txt
gpt_terminal-0.1.11.dist-info/RECORD
