Metadata-Version: 2.1
Name: gpt-terminal
Version: 0.1.11
Summary: GPT-Terminal - power AI based system.
Home-page: https://github.com/Plim4ik/GPTerminal
Author: Plim4ik
Author-email: quantumstack01@gmail.com
Project-URL: GitHub, https://github.com/Plim4ik/GPTerminal
Keywords: gpt terminal gpterminal openai
Classifier: Programming Language :: Python :: 3.11
Classifier: License :: OSI Approved :: MIT License
Classifier: Operating System :: OS Independent
Requires-Python: >=3.8
License-File: LICENSE
Requires-Dist: aiohttp ==3.8.6
Requires-Dist: aiosignal ==1.3.1
Requires-Dist: async-timeout ==4.0.3
Requires-Dist: attrs ==23.1.0
Requires-Dist: certifi ==2023.7.22
Requires-Dist: charset-normalizer ==3.3.2
Requires-Dist: frozenlist ==1.4.0
Requires-Dist: idna ==3.4
Requires-Dist: multidict ==6.0.4
Requires-Dist: openai ==0.28.0
Requires-Dist: requests ==2.31.0
Requires-Dist: tqdm ==4.66.1
Requires-Dist: urllib3 ==2.1.0
Requires-Dist: yarl ==1.9.2
